ya_fattura_elettronica_generator/IFatturaElettronicaGenerator.py
ya_fattura_elettronica_generator/IFatturaElettronicaValidator.py
ya_fattura_elettronica_generator/RegimeForfettarioFatturaElettronicaGenerator.py
ya_fattura_elettronica_generator/__init__.py
ya_fattura_elettronica_generator/main.py
ya_fattura_elettronica_generator/models.py
ya_fattura_elettronica_generator/models_stub.py
ya_fattura_elettronica_generator/utils.py
ya_fattura_elettronica_generator/validations.py
ya_fattura_elettronica_generator/version.py
ya_fattura_elettronica_generator/package_data/Schema_del_file_xml_FatturaPA_versione_1.2.xsd
ya_fattura_elettronica_generator-1.3.2.dist-info/LICENSE.md
ya_fattura_elettronica_generator-1.3.2.dist-info/METADATA
ya_fattura_elettronica_generator-1.3.2.dist-info/WHEEL
ya_fattura_elettronica_generator-1.3.2.dist-info/entry_points.txt
ya_fattura_elettronica_generator-1.3.2.dist-info/top_level.txt
ya_fattura_elettronica_generator-1.3.2.dist-info/RECORD
